giskard/__init__.py
giskard/align/__init__.py
giskard/align/align.py
giskard/embed/__init__.py
giskard/embed/embed.py
giskard/flow/__init__.py
giskard/flow/flow.py
giskard/graph/__init__.py
giskard/graph/maggot_graph.py
giskard/hierarchy/__init__.py
giskard/hierarchy/base.py
giskard/hierarchy/leiden_tree.py
giskard/hierarchy/spectral_tree.py
giskard/plot/__init__.py
giskard/plot/bar.py
giskard/plot/bar_dendrogram.py
giskard/plot/confusion.py
giskard/plot/graph_layout.py
giskard/plot/hist.py
giskard/plot/matrix.py
giskard/plot/matrixgrid.py
giskard/plot/old_matrixplot.py
giskard/plot/pairplot.py
giskard/plot/palette.py
giskard/plot/scatter.py
giskard/plot/subuniformity.py
giskard/plot/theme.py
giskard/plot/tree.py
giskard/plot/tree_hier.py
giskard/plot/utils.py
giskard/stats/__init__.py
giskard/stats/discrim.py
giskard/utils/__init__.py
giskard/utils/utils.py
giskard/utils/wrangle.py
giskard_toolbox-0.1.0.dist-info/LICENSE
giskard_toolbox-0.1.0.dist-info/METADATA
giskard_toolbox-0.1.0.dist-info/WHEEL
giskard_toolbox-0.1.0.dist-info/top_level.txt
giskard_toolbox-0.1.0.dist-info/RECORD
