Metadata-Version: 2.1
Name: giskard-toolbox
Version: 0.1.0
Summary: A random collection of tools I find useful for data science.
Home-page: https://github.com/bdpedigo/giskard
Author: Benjamin Pedigo
License: UNKNOWN
Project-URL: Bug Reports, https://github.com/bdpedigo/giskard/issues
Project-URL: Source, https://github.com/bdpedigo/giskard/
Keywords: data science,plotting
Platform: UNKNOWN
Classifier: Development Status :: 3 - Alpha
Classifier: Intended Audience :: Developers
Classifier: Topic :: Scientific/Engineering
Classifier: Topic :: Scientific/Engineering :: Visualization
Classifier: Topic :: Scientific/Engineering :: Information Analysis
Classifier: License :: OSI Approved :: MIT License
Classifier: Programming Language :: Python :: 3
Classifier: Programming Language :: Python :: 3.7
Classifier: Programming Language :: Python :: 3.8
Classifier: Programming Language :: Python :: 3.9
Classifier: Programming Language :: Python :: 3 :: Only
Requires-Python: >=3.7, <4
License-File: LICENSE
Requires-Dist: adjustText
Requires-Dist: colorcet
Requires-Dist: graspologic-native
Requires-Dist: hyppo (>=0.1.3)
Requires-Dist: joblib (>=0.17.0)
Requires-Dist: matplotlib (>=3.3.2)
Requires-Dist: numpy (>=1.8.1)
Requires-Dist: seaborn (>=0.11.0)
Requires-Dist: scikit-learn (>=0.19.1)
Requires-Dist: scipy (>=1.4.0)
Requires-Dist: umap-learn
